{"wager_limit": 100.0, "profit": [0.11100000000000057, 0.11499999999999978], "bets": [{"bookmaker": "BETRIVERS", "bet_type": "AsianHandicap", "value": "home 0.0", "odds": 1.72, "wager": 0.07}, {"bookmaker": "BETFAIR", "bet_type": "MatchWinner", "value": "Away", "odds": 3.5, "volume": 5.53, "wager": 0.05}, {"bookmaker": "BETRIVERS", "bet_type": "MatchWinner", "value": "draw", "odds": 3.1, "wager": 6.92}, {"bookmaker": "BETFAIR", "bet_type": "MatchWinner", "value": "Home", "odds": 2.54, "volume": 9.79, "wager": 0.02}, {"bookmaker": "BETFAIR", "bet_type": "MatchWinner", "value": "Draw", "odds": 3.1, "lay": true, "volume": 161.82, "wager": 0.02}, {"bookmaker": "BETFAIR", "bet_type": "MatchWinner", "value": "Draw", "odds": 3.05, "lay": true, "volume": 7.0, "wager": 6.98}], "results_table": [{"result": ["Stake returned", "Loses", "Wins", "Loses", "Lay loses", "Lay loses"], "profit": 0.11100000000000065}, {"result": ["Loses", "Wins", "Loses", "Loses", "Lay wins", "Lay wins"], "profit": 0.11500000000000021}, {"result": ["Wins", "Loses", "Loses", "Wins", "Lay wins", "Lay wins"], "profit": 0.11120000000000019}]}